parquet_dataset/__init__.py
parquet_dataset/pytorch/__init__.py
parquet_dataset/pytorch/base_parquet_dataset.py
parquet_dataset-0.0.1.dev4.dist-info/LICENSE
parquet_dataset-0.0.1.dev4.dist-info/METADATA
parquet_dataset-0.0.1.dev4.dist-info/WHEEL
parquet_dataset-0.0.1.dev4.dist-info/top_level.txt
parquet_dataset-0.0.1.dev4.dist-info/RECORD
