Metadata-Version: 2.1
Name: parquet-dataset
Version: 0.0.1.dev4
Summary: Dataset for parquet group
Home-page: UNKNOWN
Author: yslee
Author-email: yslee.dev@gmail.com
Maintainer: yslee
Maintainer-email: yslee.dev@gamil.com
License: MIT
Project-URL: Source, https://github.com/rapidrabbit76/parquet-dataset
Keywords: parquet pytorch dataset
Platform: UNKNOWN
Requires-Python: >=3.6
Requires-Dist: pandas (>=1.4.1)
Requires-Dist: pyarrow (>=7.0.0)
Requires-Dist: torch (>=1.6)
